{
  "schemaVersion": 1,
  "source": "godot",
  "baseline": "4.7-stable",
  "generatorVersion": "T-0242",
  "class": {
    "name": "CompressedTexture3D",
    "namespace": "Godot",
    "fullName": "Godot.CompressedTexture3D",
    "kind": "class",
    "baseType": "Texture3D",
    "interfaces": [],
    "godotReference": "CompressedTexture3D",
    "documentationPath": "doc/classes/CompressedTexture3D.xml",
    "documentationUrl": "https://docs.godotengine.org/en/4.7/classes/class_compressedtexture3d.html"
  },
  "constructors": [],
  "members": [
    {
      "name": "Load",
      "kind": "Method",
      "signature": "public int Load(String path)",
      "returnType": "int",
      "parameters": [
        {
          "name": "path",
          "type": "String"
        }
      ],
      "summary": "Loads the texture from the specified [param path].",
      "godotName": "load",
      "xmlDocId": "M:Godot.CompressedTexture3D.Load(String)",
      "sourcePath": "doc/classes/CompressedTexture3D.xml"
    },
    {
      "name": "LoadPath",
      "kind": "Property",
      "signature": "public String LoadPath { get; set; }",
      "returnType": "String",
      "parameters": [],
      "summary": "The [CompressedTexture3D]\u0027s file path to a [code].ctex3d[/code] file.",
      "defaultValue": "\u0022\u0022",
      "godotName": "load_path",
      "xmlDocId": "P:Godot.CompressedTexture3D.LoadPath",
      "sourcePath": "doc/classes/CompressedTexture3D.xml"
    }
  ],
  "rawMembers": [],
  "signals": [],
  "enums": [],
  "constants": [],
  "operators": [],
  "virtualMethods": [],
  "sourceInputs": [
    {
      "path": "doc/classes/CompressedTexture3D.xml",
      "sha256": "cfd6066946968e5d9b8c87fad3f7f3a86ae5cd08b6f3f1b30554a5b0b97a602b"
    },
    {
      "path": "csharp_api.json",
      "sha256": "957d4c378daa92b8deb2990c22a6fe3cff076822091a2b84daf513ba2497fd44"
    }
  ]
}
